cykooz.resizer-3.1.0.dist-info/METADATA
cykooz.resizer-3.1.0.dist-info/WHEEL
cykooz.resizer-3.1.0.dist-info/licenses/LICENSE-APACHE
cykooz.resizer-3.1.0.dist-info/licenses/LICENSE-MIT
cykooz/__init__.py
cykooz/resizer/rust_lib.pyi
cykooz/resizer/__init__.py
cykooz/resizer/structs.py
cykooz/resizer/resize.py
cykooz/resizer/alpha.py
cykooz/resizer/rust_lib.cpython-311-darwin.so
cykooz.resizer-3.1.0.dist-info/RECORD
