Metadata-Version: 2.4
Name: cykooz.resizer
Version: 3.1.0
Classifier: Development Status :: 5 - Production/Stable
Classifier: Programming Language :: Python
Classifier: Programming Language :: Python :: 3
Classifier: Programming Language :: Python :: 3.9
Classifier: Programming Language :: Python :: 3.10
Classifier: Programming Language :: Python :: 3.11
Classifier: Programming Language :: Python :: 3.12
Classifier: Programming Language :: Python :: 3.13
Classifier: Programming Language :: Python :: Implementation :: CPython
Classifier: Programming Language :: Rust
Classifier: Topic :: Multimedia :: Graphics
Classifier: Topic :: Multimedia :: Graphics :: Graphics Conversion
Classifier: License :: OSI Approved :: MIT License
Classifier: License :: OSI Approved :: Apache Software License
Requires-Dist: wheel ; extra == 'dev'
Requires-Dist: maturin[zig] ; extra == 'dev'
Requires-Dist: maturin[zig,patchelf] ; platform_system == 'Linux' and extra == 'dev'
Requires-Dist: pytest ; extra == 'dev'
Requires-Dist: pytest-benchmark ; extra == 'dev'
Requires-Dist: pillow ; extra == 'dev'
Requires-Dist: tabulate ; extra == 'dev'
Requires-Dist: pillow ; extra == 'pillow'
Provides-Extra: dev
Provides-Extra: pillow
License-File: LICENSE-APACHE
License-File: LICENSE-MIT
Summary: A fast image resizer
Keywords: image,resize,simd
Author: Kirill Kuzminykh <cykooz@gmail.com>
Author-email: Kirill Kuzminykh <cykooz@gmail.com>
Requires-Python: >=3.9
Project-URL: Homepage, https://github.com/Cykooz/cykooz.resizer
Project-URL: Repository, https://github.com/Cykooz/cykooz.resizer.git
